flask_wdb_hook/__init__.py
flask_wdb_hook-0.1.2.data/data/lib/python3.6/site-packages/flask-wdb.pth
flask_wdb_hook-0.1.2.dist-info/DESCRIPTION.rst
flask_wdb_hook-0.1.2.dist-info/METADATA
flask_wdb_hook-0.1.2.dist-info/RECORD
flask_wdb_hook-0.1.2.dist-info/WHEEL
flask_wdb_hook-0.1.2.dist-info/metadata.json
flask_wdb_hook-0.1.2.dist-info/top_level.txt
