Metadata-Version: 2.0
Name: flask-wdb-hook
Version: 0.1.2
Summary: Hook to replace flask werkzeug debugger with wdb.
Home-page: http://github.com/Kozea/wdb
Author: Florian Mounier @ kozea
Author-email: florian.mounier@kozea.fr
License: GPLv3
Platform: UNKNOWN
Requires-Dist: wdb (>=3.1.4)
